jsonschema_cli2/__init__.py
jsonschema_cli2/__main__.py
jsonschema_cli2/args.py
jsonschema_cli2/cli.py
jsonschema_cli2/exceptions.py
jsonschema_cli2/handlers.py
jsonschema_cli2/load.py
jsonschema_cli2/resolvers.py
jsonschema_cli2/tests/test_cli.py
jsonschema_cli2-1.3.2.dist-info/LICENSE
jsonschema_cli2-1.3.2.dist-info/METADATA
jsonschema_cli2-1.3.2.dist-info/WHEEL
jsonschema_cli2-1.3.2.dist-info/entry_points.txt
jsonschema_cli2-1.3.2.dist-info/RECORD
