Metadata-Version: 2.1
Name: jsonschema-cli2
Version: 1.3.2
Summary: A thin wrapper over to allow validating schemas easily using simple CLI commands.
Author: solairen
Author-email: solairen@solairen.tech
Requires-Python: >=3.8
Classifier: Development Status :: 5 - Production/Stable
Classifier: Environment :: Console
Classifier: Intended Audience :: Developers
Classifier: License :: OSI Approved :: GNU General Public License v3 or later (GPLv3+)
Classifier: Operating System :: OS Independent
Classifier: Programming Language :: Python
Classifier: Programming Language :: Python :: 3
Classifier: Programming Language :: Python :: 3.8
Classifier: Programming Language :: Python :: 3.9
Classifier: Programming Language :: Python :: 3.10
Classifier: Programming Language :: Python :: 3.11
Classifier: Programming Language :: Python :: 3.12
Classifier: Programming Language :: Python :: 3 :: Only
Classifier: Programming Language :: Python :: Implementation :: CPython
Classifier: Programming Language :: Python :: Implementation :: PyPy
Requires-Dist: jsonschema (>=3.2.0)
Requires-Dist: pyyaml (>=5.3.1)
Project-URL: Homepage, https://github.com/solairen/jsonschema_cli2
Project-URL: Issues, https://github.com/solairen/jsonschema_cli2/issues
Project-URL: Source, https://github.com/solairen/jsonschema_cli2
